statute_serial_number/__init__.py
statute_serial_number/__main__.py
statute_serial_number-0.0.3.dist-info/WHEEL
statute_serial_number-0.0.3.dist-info/METADATA
statute_serial_number-0.0.3.dist-info/RECORD
